fqn_decorators/__init__.py
fqn_decorators/asynchronous.py
fqn_decorators/decorators.py
fqn_decorators-2.0.2.dist-info/LICENSE
fqn_decorators-2.0.2.dist-info/METADATA
fqn_decorators-2.0.2.dist-info/WHEEL
fqn_decorators-2.0.2.dist-info/top_level.txt
fqn_decorators-2.0.2.dist-info/RECORD
