Metadata-Version: 2.1
Name: fqn-decorators
Version: 2.0.2
Summary: Easily create multi-purpose decorators that have access to the FQN of the original function.
Home-page: https://github.com/kpn-digital/py-fqn-decorators
Author: Mattias Sluis
Author-email: mattias.sluis@kpn.com
License: UNKNOWN
Platform: UNKNOWN
Classifier: Development Status :: 5 - Production/Stable
Classifier: Environment :: Web Environment
Classifier: Intended Audience :: Developers
Classifier: Operating System :: OS Independent
Classifier: Programming Language :: Python
Classifier: Programming Language :: Python :: 3
Classifier: Programming Language :: Python :: 3.6
Classifier: Programming Language :: Python :: 3.7
Classifier: Programming Language :: Python :: 3.8
Classifier: Topic :: Internet :: WWW/HTTP
License-File: LICENSE
